calmjs-3.4.3-py3.9-nspkg.pth
calmjs/README.rst
calmjs/argparse.py
calmjs/artifact.py
calmjs/base.py
calmjs/calmjs.py
calmjs/cli.py
calmjs/command.py
calmjs/dist.py
calmjs/exc.py
calmjs/indexer.py
calmjs/interrogate.py
calmjs/loaderplugin.py
calmjs/module.py
calmjs/npm.py
calmjs/registry.py
calmjs/runtime.py
calmjs/toolchain.py
calmjs/ui.py
calmjs/utils.py
calmjs/vlqsm.py
calmjs/yarn.py
calmjs/testing/__init__.py
calmjs/testing/artifact.py
calmjs/testing/mocks.py
calmjs/testing/module.py
calmjs/testing/spec.py
calmjs/testing/utils.py
calmjs/testing/module1/__init__.py
calmjs/testing/module1/hello.js
calmjs/testing/module2/__init__.py
calmjs/testing/module2/helper.js
calmjs/testing/module2/index.js
calmjs/testing/module2/mod/helper.js
calmjs/testing/module3/__init__.py
calmjs/testing/module3/math.js
calmjs/testing/module3/module.py
calmjs/testing/module3/runtime.py
calmjs/testing/module3/mod/index.js
calmjs/testing/module4/__init__.py
calmjs/testing/module4/data.json
calmjs/testing/module4/other.css
calmjs/testing/module4/widget.js
calmjs/testing/module4/widget.style
calmjs/testing/names/typical.js
calmjs/testing/names/unusual.js
calmjs/tests/__init__.py
calmjs/tests/test_argparse.py
calmjs/tests/test_artifact.py
calmjs/tests/test_base.py
calmjs/tests/test_cli.py
calmjs/tests/test_command.py
calmjs/tests/test_dist.py
calmjs/tests/test_indexer.py
calmjs/tests/test_interrogate.py
calmjs/tests/test_loaderplugin.py
calmjs/tests/test_module.py
calmjs/tests/test_npm.py
calmjs/tests/test_registry.py
calmjs/tests/test_runtime.py
calmjs/tests/test_testing.py
calmjs/tests/test_toolchain.py
calmjs/tests/test_ui.py
calmjs/tests/test_utils.py
calmjs/tests/test_vlqsm.py
calmjs/tests/test_yarn.py
calmjs-3.4.3.dist-info/LICENSE
calmjs-3.4.3.dist-info/METADATA
calmjs-3.4.3.dist-info/WHEEL
calmjs-3.4.3.dist-info/entry_points.txt
calmjs-3.4.3.dist-info/namespace_packages.txt
calmjs-3.4.3.dist-info/top_level.txt
calmjs-3.4.3.dist-info/RECORD
